SPODESext/parameters.py
SPODESext/task.py
test/test_tasks.py
spodesext-0.0.8.dist-info/METADATA
spodesext-0.0.8.dist-info/WHEEL
spodesext-0.0.8.dist-info/top_level.txt
spodesext-0.0.8.dist-info/RECORD
