Metadata-Version: 2.4
Name: SPODESext
Version: 0.0.8
Summary: extiontions over DLMS
Author-email: Serj Kotilevski <youserj@outlook.com>
Project-URL: Source, https://github.com/youserj/SPODESext_prj
Keywords: DLMS,spodes,extentions,SPODES
Classifier: Programming Language :: Python :: 3
Classifier: License :: OSI Approved :: MIT License
Classifier: Operating System :: OS Independent
Requires-Python: >=3.12
Requires-Dist: DLMS_SPODES_client<0.20,>=0.19.13
Requires-Dist: DLMS_SPODES>=0.87.7
Provides-Extra: dev
Requires-Dist: mypy>=1.5.0; extra == "dev"
Requires-Dist: ruff>=0.11; extra == "dev"
Requires-Dist: types-requests; extra == "dev"
